MANIFEST.in
README.md
setup.py
regme/__init__.py
regme/documents.py
regme/forms.py
regme/models.py
regme/urls.py
regme/views.py
regme.egg-info/PKG-INFO
regme.egg-info/SOURCES.txt
regme.egg-info/dependency_links.txt
regme.egg-info/requires.txt
regme.egg-info/top_level.txt
regme/templates/registration/activate.html
regme/templates/registration/activated.html
regme/templates/registration/register.html
regme/templates/registration/registered.html
regme/templates/registration/email/activate_email.txt
regme/templates/registration/email/activate_subject.txt