Metadata-Version: 1.1
Name: regme
Version: 0.2.5
Summary: User registration and management library using MongoEngine
Home-page: https://github.com/lig/regme
Author: Serge Matveenko
Author-email: s@matveenko.ru
License: Apache
Keywords: mongodb mongoengine django registration authentication
Platform: UNKNOWN
Classifier: Development Status :: 4 - Beta
Classifier: Intended Audience :: Developers
Classifier: License :: OSI Approved :: Apache Software License
Classifier: Programming Language :: Python :: 3
Classifier: Topic :: Database
Classifier: Framework :: Django
